temperature_expansion_kit_plugin/__init__.py
temperature_expansion_kit_plugin/additional_config.ini
temperature_expansion_kit_plugin/max31865.py
temperature_expansion_kit_plugin/post_install.sh
temperature_expansion_kit_plugin/ui/contrib/charts/temperature_downsampled.yaml
temperature_expansion_kit_plugin-0.3.1.dist-info/LICENSE.txt
temperature_expansion_kit_plugin-0.3.1.dist-info/METADATA
temperature_expansion_kit_plugin-0.3.1.dist-info/WHEEL
temperature_expansion_kit_plugin-0.3.1.dist-info/entry_points.txt
temperature_expansion_kit_plugin-0.3.1.dist-info/top_level.txt
temperature_expansion_kit_plugin-0.3.1.dist-info/RECORD
