Metadata-Version: 2.1
Name: temperature-expansion-kit-plugin
Version: 0.3.1
Summary: This plugin is necessary to use the temperature expansion kit for the Pioreactor
Home-page: https://github.com/Pioreactor/temperature-expansion-kit-plugin
Author: Pioreactor
Author-email: hello@pioreactor.com
License: MIT
License-File: LICENSE.txt
